{"@context":{"sameAs":{"@id":"http://www.w3.org/2002/07/owl#sameAs","@type":"@id"},"knows":"http://xmlns.com/foaf/0.1/knows"},"@id":"http://id.ndl.go.jp/auth/entity/00002506","sameAs":"http://ja.dbpedia.org/resource/青山秀夫","knows":[{"@id":"http://id.ndl.go.jp/auth/entity/00095608","sameAs":"http://ja.dbpedia.org/resource/安井琢磨"},{"@id":"http://id.ndl.go.jp/auth/entity/00460377","sameAs":"http://ja.dbpedia.org/resource/マックス・ヴェーバー"},{"@id":"http://id.ndl.go.jp/auth/entity/00082985","sameAs":"http://ja.dbpedia.org/resource/建元正弘"},{"@id":"http://id.ndl.go.jp/auth/entity/00047411","sameAs":"http://ja.dbpedia.org/resource/森嶋通夫"},{"@id":"http://id.ndl.go.jp/auth/entity/00079213","sameAs":"http://ja.dbpedia.org/resource/高田保馬"},{"@id":"http://id.ndl.go.jp/auth/entity/00047083","sameAs":"http://ja.dbpedia.org/resource/森口親司"},{"@id":"http://id.ndl.go.jp/auth/entity/01127591","sameAs":"http://ja.dbpedia.org/resource/玄鎮健"},{"@id":"http://id.ndl.go.jp/auth/entity/00889115","sameAs":"http://ja.dbpedia.org/resource/金東仁"}]}