{"@context":{"sameAs":{"@id":"http://www.w3.org/2002/07/owl#sameAs","@type":"@id"},"knows":"http://xmlns.com/foaf/0.1/knows"},"@id":"http://id.ndl.go.jp/auth/entity/00006898","sameAs":"http://ja.dbpedia.org/resource/花森安治","knows":[{"@id":"http://id.ndl.go.jp/auth/entity/00086594","sameAs":"http://ja.dbpedia.org/resource/津野海太郎"},{"@id":"http://id.ndl.go.jp/auth/entity/00103893","sameAs":"http://ja.dbpedia.org/resource/宮脇俊三"},{"@id":"http://id.ndl.go.jp/auth/entity/00046734","sameAs":"http://ja.dbpedia.org/resource/森茉莉"},{"@id":"http://id.ndl.go.jp/auth/entity/00058244","sameAs":"http://ja.dbpedia.org/resource/扇谷正造"},{"@id":"http://id.ndl.go.jp/auth/entity/00551435","sameAs":"http://ja.dbpedia.org/resource/フリッツ・カルシュ"},{"@id":"http://id.ndl.go.jp/auth/entity/00016195","sameAs":"http://ja.dbpedia.org/resource/藤城清治"},{"@id":"http://id.ndl.go.jp/auth/entity/00074631","sameAs":"http://ja.dbpedia.org/resource/杉浦明平"},{"@id":"http://id.ndl.go.jp/auth/entity/00059598","sameAs":"http://ja.dbpedia.org/resource/岡倉古志郎"},{"@id":"http://id.ndl.go.jp/auth/entity/00080966","sameAs":"http://ja.dbpedia.org/resource/田宮虎彦"},{"@id":"http://id.ndl.go.jp/auth/entity/00038122","sameAs":"http://ja.dbpedia.org/resource/黒田恭一"}]}