{"@context":{"sameAs":{"@id":"http://www.w3.org/2002/07/owl#sameAs","@type":"@id"},"knows":"http://xmlns.com/foaf/0.1/knows"},"@id":"http://id.ndl.go.jp/auth/entity/00034884","sameAs":"http://ja.dbpedia.org/resource/小室直樹","knows":[{"@id":"http://id.ndl.go.jp/auth/entity/001117230","sameAs":"http://ja.dbpedia.org/resource/吉原毅"},{"@id":"http://id.ndl.go.jp/auth/entity/00043882","sameAs":"http://ja.dbpedia.org/resource/三島由紀夫"},{"@id":"http://id.ndl.go.jp/auth/entity/00186290","sameAs":"http://ja.dbpedia.org/resource/宮台真司"},{"@id":"http://id.ndl.go.jp/auth/entity/00063543","sameAs":"http://ja.dbpedia.org/resource/大塚久雄"},{"@id":"http://id.ndl.go.jp/auth/entity/00082732","sameAs":"http://ja.dbpedia.org/resource/谷沢永一"},{"@id":"http://id.ndl.go.jp/auth/entity/00369214","sameAs":"http://ja.dbpedia.org/resource/片倉邦雄"},{"@id":"http://id.ndl.go.jp/auth/entity/00040256","sameAs":"http://ja.dbpedia.org/resource/丸山眞男"},{"@id":"http://id.ndl.go.jp/auth/entity/00091086","sameAs":"http://ja.dbpedia.org/resource/渡部昇一"},{"@id":"http://id.ndl.go.jp/auth/entity/00921082","sameAs":"http://ja.dbpedia.org/resource/深田匠"},{"@id":"http://id.ndl.go.jp/auth/entity/00197551","sameAs":"http://ja.dbpedia.org/resource/副島隆彦"},{"@id":"http://id.ndl.go.jp/auth/entity/00455833","sameAs":"http://ja.dbpedia.org/resource/ヨーゼフ・シュンペーター"},{"@id":"http://id.ndl.go.jp/auth/entity/00047411","sameAs":"http://ja.dbpedia.org/resource/森嶋通夫"},{"@id":"http://id.ndl.go.jp/auth/entity/00037944","sameAs":"http://ja.dbpedia.org/resource/栗本慎一郎"},{"@id":"http://id.ndl.go.jp/auth/entity/00142812","sameAs":"http://ja.dbpedia.org/resource/景山民夫"},{"@id":"http://id.ndl.go.jp/auth/entity/00874575","sameAs":"http://ja.dbpedia.org/resource/栗林忠道"},{"@id":"http://id.ndl.go.jp/auth/entity/00002074","sameAs":"http://ja.dbpedia.org/resource/青井和夫"},{"@id":"http://id.ndl.go.jp/auth/entity/00141192","sameAs":"http://ja.dbpedia.org/resource/盛山和夫"},{"@id":"http://id.ndl.go.jp/auth/entity/00082971","sameAs":"http://ja.dbpedia.org/resource/立川談志"},{"@id":"http://id.ndl.go.jp/auth/entity/00455249","sameAs":"http://ja.dbpedia.org/resource/ポール・サミュエルソン"},{"@id":"http://id.ndl.go.jp/auth/entity/00271199","sameAs":"http://ja.dbpedia.org/resource/二宮尊徳"},{"@id":"http://id.ndl.go.jp/auth/entity/00098302","sameAs":"http://ja.dbpedia.org/resource/湯川秀樹"},{"@id":"http://id.ndl.go.jp/auth/entity/00064225","sameAs":"http://ja.dbpedia.org/resource/小沢遼子"},{"@id":"http://id.ndl.go.jp/auth/entity/00084953","sameAs":"http://ja.dbpedia.org/resource/富永健一"},{"@id":"http://id.ndl.go.jp/auth/entity/00081551","sameAs":"http://ja.dbpedia.org/resource/田中角栄"},{"@id":"http://id.ndl.go.jp/auth/entity/00460377","sameAs":"http://ja.dbpedia.org/resource/マックス・ヴェーバー"},{"@id":"http://id.ndl.go.jp/auth/entity/00431773","sameAs":"http://ja.dbpedia.org/resource/ケネス・アロー"},{"@id":"http://id.ndl.go.jp/auth/entity/00184169","sameAs":"http://ja.dbpedia.org/resource/大澤真幸"},{"@id":"http://id.ndl.go.jp/auth/entity/00443272","sameAs":"http://ja.dbpedia.org/resource/ジョン・ヒックス"},{"@id":"http://id.ndl.go.jp/auth/entity/00079213","sameAs":"http://ja.dbpedia.org/resource/高田保馬"},{"@id":"http://id.ndl.go.jp/auth/entity/00443695","sameAs":"http://ja.dbpedia.org/resource/ジョージ・ホーマンズ"},{"@id":"http://id.ndl.go.jp/auth/entity/00456770","sameAs":"http://ja.dbpedia.org/resource/バラス・スキナー"},{"@id":"http://id.ndl.go.jp/auth/entity/00072381","sameAs":"http://ja.dbpedia.org/resource/篠原一_(政治学者)"},{"@id":"http://id.ndl.go.jp/auth/entity/00213507","sameAs":"http://ja.dbpedia.org/resource/志田基与師"},{"@id":"http://id.ndl.go.jp/auth/entity/00037603","sameAs":"http://ja.dbpedia.org/resource/倉前盛通"},{"@id":"http://id.ndl.go.jp/auth/entity/00095608","sameAs":"http://ja.dbpedia.org/resource/安井琢磨"},{"@id":"http://id.ndl.go.jp/auth/entity/00029817","sameAs":"http://ja.dbpedia.org/resource/川島武宜"},{"@id":"http://id.ndl.go.jp/auth/entity/00452203","sameAs":"http://ja.dbpedia.org/resource/タルコット・パーソンズ"},{"@id":"http://id.ndl.go.jp/auth/entity/00055436","sameAs":"http://ja.dbpedia.org/resource/西尾幹二"},{"@id":"http://id.ndl.go.jp/auth/entity/00150747","sameAs":"http://ja.dbpedia.org/resource/橋爪大三郎"},{"@id":"http://id.ndl.go.jp/auth/entity/00052309","sameAs":"http://ja.dbpedia.org/resource/中根千枝"},{"@id":"http://id.ndl.go.jp/auth/entity/00038587","sameAs":"http://ja.dbpedia.org/resource/日下公人"},{"@id":"http://id.ndl.go.jp/auth/entity/00123603","sameAs":"http://ja.dbpedia.org/resource/渡部恒三"},{"@id":"http://id.ndl.go.jp/auth/entity/00096169","sameAs":"http://ja.dbpedia.org/resource/横田喜三郎"},{"@id":"http://id.ndl.go.jp/auth/entity/00093525","sameAs":"http://ja.dbpedia.org/resource/山本七平"},{"@id":"http://id.ndl.go.jp/auth/entity/00315627","sameAs":"http://ja.dbpedia.org/resource/色摩力夫"},{"@id":"http://id.ndl.go.jp/auth/entity/00016572","sameAs":"http://ja.dbpedia.org/resource/藤原弘達"},{"@id":"http://id.ndl.go.jp/auth/entity/00460122","sameAs":"http://ja.dbpedia.org/resource/レオン・ワルラス"},{"@id":"http://id.ndl.go.jp/auth/entity/00039123","sameAs":"http://ja.dbpedia.org/resource/京極純一"},{"@id":"http://id.ndl.go.jp/auth/entity/00054540","sameAs":"http://ja.dbpedia.org/resource/二階堂副包"},{"@id":"http://id.ndl.go.jp/auth/entity/00018377","sameAs":"http://ja.dbpedia.org/resource/今田高俊"},{"@id":"http://id.ndl.go.jp/auth/entity/00457147","sameAs":"http://ja.dbpedia.org/resource/ロバート・ソロー"},{"@id":"http://id.ndl.go.jp/auth/entity/00028223","sameAs":"http://ja.dbpedia.org/resource/加藤芳郎"},{"@id":"http://id.ndl.go.jp/auth/entity/00131160","sameAs":"http://ja.dbpedia.org/resource/猪瀬直樹"},{"@id":"http://id.ndl.go.jp/auth/entity/00417625","sameAs":"http://ja.dbpedia.org/resource/杉原千畝"},{"@id":"http://id.ndl.go.jp/auth/entity/00022247","sameAs":"http://ja.dbpedia.org/resource/市川宏_(中国文学者)"},{"@id":"http://id.ndl.go.jp/auth/entity/00189559","sameAs":"http://ja.dbpedia.org/resource/土田正顕"},{"@id":"http://id.ndl.go.jp/auth/entity/00085635","sameAs":"http://ja.dbpedia.org/resource/戸塚宏"},{"@id":"http://id.ndl.go.jp/auth/entity/00085935","sameAs":"http://ja.dbpedia.org/resource/東條英機"},{"@id":"http://id.ndl.go.jp/auth/entity/00127327","sameAs":"http://ja.dbpedia.org/resource/若宮清"}]}