{"@context":{"sameAs":{"@id":"http://www.w3.org/2002/07/owl#sameAs","@type":"@id"},"knows":"http://xmlns.com/foaf/0.1/knows"},"@id":"http://id.ndl.go.jp/auth/entity/00049645","sameAs":"http://ja.dbpedia.org/resource/永井潔","knows":[{"@id":"http://id.ndl.go.jp/auth/entity/00117876","sameAs":"http://ja.dbpedia.org/resource/澤田俊一"},{"@id":"http://id.ndl.go.jp/auth/entity/00108427","sameAs":"http://ja.dbpedia.org/resource/鳥居敏文"},{"@id":"http://id.ndl.go.jp/auth/entity/00079225","sameAs":"http://ja.dbpedia.org/resource/高藤武馬"},{"@id":"http://id.ndl.go.jp/auth/entity/00194184","sameAs":"http://ja.dbpedia.org/resource/永井愛"},{"@id":"http://id.ndl.go.jp/auth/entity/00045052","sameAs":"http://ja.dbpedia.org/resource/宮本顕治"},{"@id":"http://id.ndl.go.jp/auth/entity/00088658","sameAs":"http://ja.dbpedia.org/resource/梅崎春生"},{"@id":"http://id.ndl.go.jp/auth/entity/00049224","sameAs":"http://ja.dbpedia.org/resource/村山知義"},{"@id":"http://id.ndl.go.jp/auth/entity/00054881","sameAs":"http://ja.dbpedia.org/resource/西口克己"},{"@id":"http://id.ndl.go.jp/auth/entity/00009950","sameAs":"http://ja.dbpedia.org/resource/硲伊之助"},{"@id":"http://id.ndl.go.jp/auth/entity/00094217","sameAs":"http://ja.dbpedia.org/resource/山代巴"},{"@id":"http://id.ndl.go.jp/auth/entity/00059403","sameAs":"http://ja.dbpedia.org/resource/岡田三郎助"},{"@id":"http://id.ndl.go.jp/auth/entity/00684537","sameAs":"http://ja.dbpedia.org/resource/紺野修司"}]}