{"@context":{"sameAs":{"@id":"http://www.w3.org/2002/07/owl#sameAs","@type":"@id"},"knows":"http://xmlns.com/foaf/0.1/knows"},"@id":"http://id.ndl.go.jp/auth/entity/00044366","sameAs":"http://ja.dbpedia.org/resource/三浦関造","knows":[{"@id":"http://id.ndl.go.jp/auth/entity/00438157","sameAs":"http://ja.dbpedia.org/resource/フョードル・ドストエフスキー"},{"@id":"http://id.ndl.go.jp/auth/entity/00433398","sameAs":"http://ja.dbpedia.org/resource/ビョルンスティエルネ・ビョルンソン"},{"@id":"http://id.ndl.go.jp/auth/entity/00271791","sameAs":"http://ja.dbpedia.org/resource/親鸞"},{"@id":"http://id.ndl.go.jp/auth/entity/00523933","sameAs":"http://ja.dbpedia.org/resource/チェーザレ・ロンブローゾ"},{"@id":"http://id.ndl.go.jp/auth/entity/00458261","sameAs":"http://ja.dbpedia.org/resource/ラビンドラナート・タゴール"},{"@id":"http://id.ndl.go.jp/auth/entity/00446393","sameAs":"http://ja.dbpedia.org/resource/ピョートル・クロポトキン"},{"@id":"http://id.ndl.go.jp/auth/entity/00456550","sameAs":"http://ja.dbpedia.org/resource/ヘンリク・シェンキェヴィチ"},{"@id":"http://id.ndl.go.jp/auth/entity/00454830","sameAs":"http://ja.dbpedia.org/resource/ジャン＝ジャック・ルソー"},{"@id":"http://id.ndl.go.jp/auth/entity/00454557","sameAs":"http://ja.dbpedia.org/resource/ロマン・ロラン"},{"@id":"http://id.ndl.go.jp/auth/entity/00458898","sameAs":"http://ja.dbpedia.org/resource/レフ・トルストイ"}]}