{"@context":{"sameAs":{"@id":"http://www.w3.org/2002/07/owl#sameAs","@type":"@id"},"knows":"http://xmlns.com/foaf/0.1/knows"},"@id":"http://id.ndl.go.jp/auth/entity/00054642","sameAs":"http://ja.dbpedia.org/resource/西周_(啓蒙家)","knows":[{"@id":"http://id.ndl.go.jp/auth/entity/00071747","sameAs":"http://ja.dbpedia.org/resource/清水多吉"},{"@id":"http://id.ndl.go.jp/auth/entity/00220935","sameAs":"http://ja.dbpedia.org/resource/亀井茲明"},{"@id":"http://id.ndl.go.jp/auth/entity/00624726","sameAs":"http://ja.dbpedia.org/resource/赤松小三郎"},{"@id":"http://id.ndl.go.jp/auth/entity/00046801","sameAs":"http://ja.dbpedia.org/resource/森鴎外"},{"@id":"http://id.ndl.go.jp/auth/entity/00030933","sameAs":"http://ja.dbpedia.org/resource/木村芥舟"},{"@id":"http://id.ndl.go.jp/auth/entity/00291315","sameAs":"http://ja.dbpedia.org/resource/林洞海"},{"@id":"http://id.ndl.go.jp/auth/entity/00722056","sameAs":"http://ja.dbpedia.org/resource/山辺丈夫"},{"@id":"http://id.ndl.go.jp/auth/entity/00055296","sameAs":"http://ja.dbpedia.org/resource/西村茂樹"},{"@id":"http://id.ndl.go.jp/auth/entity/00000986","sameAs":"http://ja.dbpedia.org/resource/赤松則良"},{"@id":"http://id.ndl.go.jp/auth/entity/00497023","sameAs":"http://ja.dbpedia.org/resource/西道仙"},{"@id":"http://id.ndl.go.jp/auth/entity/00033937","sameAs":"http://ja.dbpedia.org/resource/古賀謹一郎"},{"@id":"http://id.ndl.go.jp/auth/entity/00027670","sameAs":"http://ja.dbpedia.org/resource/加藤弘之"},{"@id":"http://id.ndl.go.jp/auth/entity/00161832","sameAs":"http://ja.dbpedia.org/resource/内田正雄"},{"@id":"http://id.ndl.go.jp/auth/entity/00623660","sameAs":"http://ja.dbpedia.org/resource/山本覚馬"},{"@id":"http://id.ndl.go.jp/auth/entity/00108958","sameAs":"http://ja.dbpedia.org/resource/渡部温"},{"@id":"http://id.ndl.go.jp/auth/entity/00084688","sameAs":"http://ja.dbpedia.org/resource/徳川慶喜"},{"@id":"http://id.ndl.go.jp/auth/entity/00005555","sameAs":"http://ja.dbpedia.org/resource/榎本武揚"},{"@id":"http://id.ndl.go.jp/auth/entity/00025355","sameAs":"http://ja.dbpedia.org/resource/亀井節夫"},{"@id":"http://id.ndl.go.jp/auth/entity/00269732","sameAs":"http://ja.dbpedia.org/resource/堀達之助"},{"@id":"http://id.ndl.go.jp/auth/entity/00051770","sameAs":"http://ja.dbpedia.org/resource/中村正直"},{"@id":"http://id.ndl.go.jp/auth/entity/00038966","sameAs":"http://ja.dbpedia.org/resource/桑木厳翼"},{"@id":"http://id.ndl.go.jp/auth/entity/00044244","sameAs":"http://ja.dbpedia.org/resource/箕作麟祥"},{"@id":"http://id.ndl.go.jp/auth/entity/00046542","sameAs":"http://ja.dbpedia.org/resource/森有礼"},{"@id":"http://id.ndl.go.jp/auth/entity/00086080","sameAs":"http://ja.dbpedia.org/resource/津田真道"},{"@id":"http://id.ndl.go.jp/auth/entity/00034384","sameAs":"http://ja.dbpedia.org/resource/小泉仰"},{"@id":"http://id.ndl.go.jp/auth/entity/00626508","sameAs":"http://ja.dbpedia.org/resource/堀田正睦"},{"@id":"http://id.ndl.go.jp/auth/entity/00621127","sameAs":"http://ja.dbpedia.org/resource/ゲオルク・ミヒャエリス"},{"@id":"http://id.ndl.go.jp/auth/entity/001122858","sameAs":"http://ja.dbpedia.org/resource/亀井茲矩"},{"@id":"http://id.ndl.go.jp/auth/entity/00060602","sameAs":"http://ja.dbpedia.org/resource/大久保利謙"},{"@id":"http://id.ndl.go.jp/auth/entity/00269787","sameAs":"http://ja.dbpedia.org/resource/福澤諭吉"},{"@id":"http://id.ndl.go.jp/auth/entity/00043014","sameAs":"http://ja.dbpedia.org/resource/明治天皇"}]}