{"@context":{"sameAs":{"@id":"http://www.w3.org/2002/07/owl#sameAs","@type":"@id"},"knows":"http://xmlns.com/foaf/0.1/knows"},"@id":"http://id.ndl.go.jp/auth/entity/00072307","sameAs":"http://ja.dbpedia.org/resource/新村猛","knows":[{"@id":"http://id.ndl.go.jp/auth/entity/00454557","sameAs":"http://ja.dbpedia.org/resource/ロマン・ロラン"},{"@id":"http://id.ndl.go.jp/auth/entity/00457429","sameAs":"http://ja.dbpedia.org/resource/ヨシフ・スターリン"},{"@id":"http://id.ndl.go.jp/auth/entity/00120075","sameAs":"http://ja.dbpedia.org/resource/新村徹"},{"@id":"http://id.ndl.go.jp/auth/entity/00038872","sameAs":"http://ja.dbpedia.org/resource/桑原幹根"},{"@id":"http://id.ndl.go.jp/auth/entity/00018392","sameAs":"http://ja.dbpedia.org/resource/今江祥智"},{"@id":"http://id.ndl.go.jp/auth/entity/00007074","sameAs":"http://ja.dbpedia.org/resource/羽仁五郎"},{"@id":"http://id.ndl.go.jp/auth/entity/00449191","sameAs":"http://ja.dbpedia.org/resource/ギ・ド・モーパッサン"},{"@id":"http://id.ndl.go.jp/auth/entity/00080138","sameAs":"http://ja.dbpedia.org/resource/武谷三男"},{"@id":"http://id.ndl.go.jp/auth/entity/00437879","sameAs":"http://ja.dbpedia.org/resource/ドゥニ・ディドロ"},{"@id":"http://id.ndl.go.jp/auth/entity/00042721","sameAs":"http://ja.dbpedia.org/resource/松浦総三"},{"@id":"http://id.ndl.go.jp/auth/entity/00025680","sameAs":"http://ja.dbpedia.org/resource/神沢栄三"},{"@id":"http://id.ndl.go.jp/auth/entity/00431196","sameAs":"http://ja.dbpedia.org/resource/ジャン・ル・ロン・ダランベール"},{"@id":"http://id.ndl.go.jp/auth/entity/00047347","sameAs":"http://ja.dbpedia.org/resource/森岡敬一郎"},{"@id":"http://id.ndl.go.jp/auth/entity/00433537","sameAs":"http://ja.dbpedia.org/resource/マルク・ブロック"},{"@id":"http://id.ndl.go.jp/auth/entity/00051313","sameAs":"http://ja.dbpedia.org/resource/中井正一"},{"@id":"http://id.ndl.go.jp/auth/entity/00040469","sameAs":"http://ja.dbpedia.org/resource/真下信一"},{"@id":"http://id.ndl.go.jp/auth/entity/00063095","sameAs":"http://ja.dbpedia.org/resource/大高順雄"},{"@id":"http://id.ndl.go.jp/auth/entity/00080405","sameAs":"http://ja.dbpedia.org/resource/竹内良知"},{"@id":"http://id.ndl.go.jp/auth/entity/00432278","sameAs":"http://ja.dbpedia.org/resource/アンリ・バルビュス"},{"@id":"http://id.ndl.go.jp/auth/entity/00072302","sameAs":"http://ja.dbpedia.org/resource/新村出"},{"@id":"http://id.ndl.go.jp/auth/entity/00059077","sameAs":"http://ja.dbpedia.org/resource/岡茂雄"},{"@id":"http://id.ndl.go.jp/auth/entity/00037374","sameAs":"http://ja.dbpedia.org/resource/国原吉之助"},{"@id":"http://id.ndl.go.jp/auth/entity/00090729","sameAs":"http://ja.dbpedia.org/resource/渡辺一夫"},{"@id":"http://id.ndl.go.jp/auth/entity/00007976","sameAs":"http://ja.dbpedia.org/resource/長谷川正安"},{"@id":"http://id.ndl.go.jp/auth/entity/00040777","sameAs":"http://ja.dbpedia.org/resource/増山太助"},{"@id":"http://id.ndl.go.jp/auth/entity/00095578","sameAs":"http://ja.dbpedia.org/resource/安井郁"},{"@id":"http://id.ndl.go.jp/auth/entity/00071703","sameAs":"http://ja.dbpedia.org/resource/清水慎三"},{"@id":"http://id.ndl.go.jp/auth/entity/00449201","sameAs":"http://ja.dbpedia.org/resource/アンドレ・モーロワ"}]}