{"@context":{"sameAs":{"@id":"http://www.w3.org/2002/07/owl#sameAs","@type":"@id"},"knows":"http://xmlns.com/foaf/0.1/knows"},"@id":"http://id.ndl.go.jp/auth/entity/00080526","sameAs":"http://ja.dbpedia.org/resource/滝平二郎","knows":[{"@id":"http://id.ndl.go.jp/auth/entity/00117876","sameAs":"http://ja.dbpedia.org/resource/澤田俊一"},{"@id":"http://id.ndl.go.jp/auth/entity/00019344","sameAs":"http://ja.dbpedia.org/resource/井野川潔"},{"@id":"http://id.ndl.go.jp/auth/entity/00108427","sameAs":"http://ja.dbpedia.org/resource/鳥居敏文"},{"@id":"http://id.ndl.go.jp/auth/entity/00074898","sameAs":"http://ja.dbpedia.org/resource/住井すゑ"},{"@id":"http://id.ndl.go.jp/auth/entity/00027278","sameAs":"http://ja.dbpedia.org/resource/加太こうじ"},{"@id":"http://id.ndl.go.jp/auth/entity/00088826","sameAs":"http://ja.dbpedia.org/resource/宇野重吉"},{"@id":"http://id.ndl.go.jp/auth/entity/00054167","sameAs":"http://ja.dbpedia.org/resource/那須田稔"},{"@id":"http://id.ndl.go.jp/auth/entity/00031535","sameAs":"http://ja.dbpedia.org/resource/木下順二"},{"@id":"http://id.ndl.go.jp/auth/entity/00194291","sameAs":"http://ja.dbpedia.org/resource/中谷泰"},{"@id":"http://id.ndl.go.jp/auth/entity/00023993","sameAs":"http://ja.dbpedia.org/resource/いわさきちひろ"},{"@id":"http://id.ndl.go.jp/auth/entity/00684537","sameAs":"http://ja.dbpedia.org/resource/紺野修司"},{"@id":"http://id.ndl.go.jp/auth/entity/00010717","sameAs":"http://ja.dbpedia.org/resource/平井信義"},{"@id":"http://id.ndl.go.jp/auth/entity/00037309","sameAs":"http://ja.dbpedia.org/resource/久米宏一"},{"@id":"http://id.ndl.go.jp/auth/entity/00014901","sameAs":"http://ja.dbpedia.org/resource/古田足日"},{"@id":"http://id.ndl.go.jp/auth/entity/00043933","sameAs":"http://ja.dbpedia.org/resource/箕田源二郎"},{"@id":"http://id.ndl.go.jp/auth/entity/00065209","sameAs":"http://ja.dbpedia.org/resource/斎藤隆介"}]}