{"@context":{"sameAs":{"@id":"http://www.w3.org/2002/07/owl#sameAs","@type":"@id"},"knows":"http://xmlns.com/foaf/0.1/knows"},"@id":"http://id.ndl.go.jp/auth/entity/00083679","sameAs":"http://ja.dbpedia.org/resource/寺尾善雄","knows":[{"@id":"http://id.ndl.go.jp/auth/entity/00007754","sameAs":"http://ja.dbpedia.org/resource/春名徹"},{"@id":"http://id.ndl.go.jp/auth/entity/00625618","sameAs":"http://ja.dbpedia.org/resource/鄭成功"},{"@id":"http://id.ndl.go.jp/auth/entity/00334624","sameAs":"http://ja.dbpedia.org/resource/諸葛亮"},{"@id":"http://id.ndl.go.jp/auth/entity/00034491","sameAs":"http://ja.dbpedia.org/resource/駒田信二"}]}