{"@context":{"sameAs":{"@id":"http://www.w3.org/2002/07/owl#sameAs","@type":"@id"},"knows":"http://xmlns.com/foaf/0.1/knows"},"@id":"http://id.ndl.go.jp/auth/entity/00095110","sameAs":"http://ja.dbpedia.org/resource/柳澤桂子","knows":[{"@id":"http://id.ndl.go.jp/auth/entity/00012447","sameAs":"http://ja.dbpedia.org/resource/堀文子"},{"@id":"http://id.ndl.go.jp/auth/entity/00083165","sameAs":"http://ja.dbpedia.org/resource/立木義浩"},{"@id":"http://id.ndl.go.jp/auth/entity/01019850","sameAs":"http://ja.dbpedia.org/resource/梯剛之"},{"@id":"http://id.ndl.go.jp/auth/entity/00118167","sameAs":"http://ja.dbpedia.org/resource/多田富雄"},{"@id":"http://id.ndl.go.jp/auth/entity/00840728","sameAs":"http://ja.dbpedia.org/resource/玄侑宗久"}]}