{"@context":{"sameAs":{"@id":"http://www.w3.org/2002/07/owl#sameAs","@type":"@id"},"knows":"http://xmlns.com/foaf/0.1/knows"},"@id":"http://id.ndl.go.jp/auth/entity/001137997","sameAs":"http://ja.dbpedia.org/resource/井岡一翔","knows":[{"@id":"http://id.ndl.go.jp/auth/entity/01120766","sameAs":"http://ja.dbpedia.org/resource/内藤大助"},{"@id":"http://id.ndl.go.jp/auth/entity/00109606","sameAs":"http://ja.dbpedia.org/resource/矢沢永吉"},{"@id":"http://id.ndl.go.jp/auth/entity/001131541","sameAs":"http://ja.dbpedia.org/resource/八重樫東"},{"@id":"http://id.ndl.go.jp/auth/entity/00389048","sameAs":"http://ja.dbpedia.org/resource/辰吉丈一郎"},{"@id":"http://id.ndl.go.jp/auth/entity/00745815","sameAs":"http://ja.dbpedia.org/resource/平仲明信"},{"@id":"http://id.ndl.go.jp/auth/entity/00117951","sameAs":"http://ja.dbpedia.org/resource/島田紳助"},{"@id":"http://id.ndl.go.jp/auth/entity/00848832","sameAs":"http://ja.dbpedia.org/resource/竹原慎二"},{"@id":"http://id.ndl.go.jp/auth/entity/001169048","sameAs":"http://ja.dbpedia.org/resource/井上尚弥"},{"@id":"http://id.ndl.go.jp/auth/entity/01171015","sameAs":"http://ja.dbpedia.org/resource/柴田英嗣"},{"@id":"http://id.ndl.go.jp/auth/entity/01199931","sameAs":"http://ja.dbpedia.org/resource/笑福亭笑瓶"},{"@id":"http://id.ndl.go.jp/auth/entity/00149124","sameAs":"http://ja.dbpedia.org/resource/ビートたけし"},{"@id":"http://id.ndl.go.jp/auth/entity/00182676","sameAs":"http://ja.dbpedia.org/resource/渡辺正行"},{"@id":"http://id.ndl.go.jp/auth/entity/00901695","sameAs":"http://ja.dbpedia.org/resource/香川照之"},{"@id":"http://id.ndl.go.jp/auth/entity/00091433","sameAs":"http://ja.dbpedia.org/resource/輪島功一"},{"@id":"http://id.ndl.go.jp/auth/entity/001140208","sameAs":"http://ja.dbpedia.org/resource/村田諒太"}]}