{"@context":{"sameAs":{"@id":"http://www.w3.org/2002/07/owl#sameAs","@type":"@id"},"knows":"http://xmlns.com/foaf/0.1/knows"},"@id":"http://id.ndl.go.jp/auth/entity/00135646","sameAs":"http://ja.dbpedia.org/resource/森田伸子","knows":[{"@id":"http://id.ndl.go.jp/auth/entity/00052922","sameAs":"http://ja.dbpedia.org/resource/中内敏夫"},{"@id":"http://id.ndl.go.jp/auth/entity/00166929","sameAs":"http://ja.dbpedia.org/resource/今井康雄"},{"@id":"http://id.ndl.go.jp/auth/entity/00431684","sameAs":"http://ja.dbpedia.org/resource/フィリップ・アリエス"}]}