{"@context":{"sameAs":{"@id":"http://www.w3.org/2002/07/owl#sameAs","@type":"@id"},"knows":"http://xmlns.com/foaf/0.1/knows"},"@id":"http://id.ndl.go.jp/auth/entity/00136949","sameAs":"http://ja.dbpedia.org/resource/樋口修吉","knows":[{"@id":"http://id.ndl.go.jp/auth/entity/00020172","sameAs":"http://ja.dbpedia.org/resource/色川武大"},{"@id":"http://id.ndl.go.jp/auth/entity/00156420","sameAs":"http://ja.dbpedia.org/resource/安部譲二"},{"@id":"http://id.ndl.go.jp/auth/entity/00151703","sameAs":"http://ja.dbpedia.org/resource/野沢尚"},{"@id":"http://id.ndl.go.jp/auth/entity/00113256","sameAs":"http://ja.dbpedia.org/resource/逢坂剛"},{"@id":"http://id.ndl.go.jp/auth/entity/00121585","sameAs":"http://ja.dbpedia.org/resource/北方謙三"},{"@id":"http://id.ndl.go.jp/auth/entity/00117604","sameAs":"http://ja.dbpedia.org/resource/大沢在昌"},{"@id":"http://id.ndl.go.jp/auth/entity/00100395","sameAs":"http://ja.dbpedia.org/resource/船戸与一"},{"@id":"http://id.ndl.go.jp/auth/entity/00117974","sameAs":"http://ja.dbpedia.org/resource/志水辰夫"},{"@id":"http://id.ndl.go.jp/auth/entity/00046553","sameAs":"http://ja.dbpedia.org/resource/森詠"}]}