{"@context":{"sameAs":{"@id":"http://www.w3.org/2002/07/owl#sameAs","@type":"@id"},"knows":"http://xmlns.com/foaf/0.1/knows"},"@id":"http://id.ndl.go.jp/auth/entity/00142740","sameAs":"http://ja.dbpedia.org/resource/板坂剛","knows":[{"@id":"http://id.ndl.go.jp/auth/entity/00043882","sameAs":"http://ja.dbpedia.org/resource/三島由紀夫"},{"@id":"http://id.ndl.go.jp/auth/entity/00014369","sameAs":"http://ja.dbpedia.org/resource/福島次郎"},{"@id":"http://id.ndl.go.jp/auth/entity/00507592","sameAs":"http://ja.dbpedia.org/resource/平岡定太郎"},{"@id":"http://id.ndl.go.jp/auth/entity/00175480","sameAs":"http://ja.dbpedia.org/resource/小西昌幸"},{"@id":"http://id.ndl.go.jp/auth/entity/00022139","sameAs":"http://ja.dbpedia.org/resource/板坂元"},{"@id":"http://id.ndl.go.jp/auth/entity/00079998","sameAs":"http://ja.dbpedia.org/resource/竹中労"},{"@id":"http://id.ndl.go.jp/auth/entity/00084438","sameAs":"http://ja.dbpedia.org/resource/東郷健"},{"@id":"http://id.ndl.go.jp/auth/entity/01119411","sameAs":"http://ja.dbpedia.org/resource/ブルーザー・ブロディ"},{"@id":"http://id.ndl.go.jp/auth/entity/00028570","sameAs":"http://ja.dbpedia.org/resource/川端康成"},{"@id":"http://id.ndl.go.jp/auth/entity/00133536","sameAs":"http://ja.dbpedia.org/resource/ミスター高橋"},{"@id":"http://id.ndl.go.jp/auth/entity/00048568","sameAs":"http://ja.dbpedia.org/resource/村上龍"},{"@id":"http://id.ndl.go.jp/auth/entity/00098948","sameAs":"http://ja.dbpedia.org/resource/アントニオ猪木"}]}