{"@context":{"sameAs":{"@id":"http://www.w3.org/2002/07/owl#sameAs","@type":"@id"},"knows":"http://xmlns.com/foaf/0.1/knows"},"@id":"http://id.ndl.go.jp/auth/entity/00252564","sameAs":"http://ja.dbpedia.org/resource/三沢あけみ","knows":[{"@id":"http://id.ndl.go.jp/auth/entity/00123407","sameAs":"http://ja.dbpedia.org/resource/渡久地政信"},{"@id":"http://id.ndl.go.jp/auth/entity/00625604","sameAs":"http://ja.dbpedia.org/resource/鶴田浩二"},{"@id":"http://id.ndl.go.jp/auth/entity/00064004","sameAs":"http://ja.dbpedia.org/resource/大山康晴"},{"@id":"http://id.ndl.go.jp/auth/entity/00934188","sameAs":"http://ja.dbpedia.org/resource/吉川静夫"}]}