{"@context":{"sameAs":{"@id":"http://www.w3.org/2002/07/owl#sameAs","@type":"@id"},"knows":"http://xmlns.com/foaf/0.1/knows"},"@id":"http://id.ndl.go.jp/auth/entity/00269155","sameAs":"http://ja.dbpedia.org/resource/阿仏尼","knows":[{"@id":"http://id.ndl.go.jp/auth/entity/00847091","sameAs":"http://ja.dbpedia.org/resource/田渕句美子"},{"@id":"http://id.ndl.go.jp/auth/entity/00020566","sameAs":"http://ja.dbpedia.org/resource/石田吉貞"},{"@id":"http://id.ndl.go.jp/auth/entity/00047237","sameAs":"http://ja.dbpedia.org/resource/森本元子"},{"@id":"http://id.ndl.go.jp/auth/entity/00269900","sameAs":"http://ja.dbpedia.org/resource/藤原為家"},{"@id":"http://id.ndl.go.jp/auth/entity/00049753","sameAs":"http://ja.dbpedia.org/resource/永井義憲"},{"@id":"http://id.ndl.go.jp/auth/entity/00086192","sameAs":"http://ja.dbpedia.org/resource/次田香澄"},{"@id":"http://id.ndl.go.jp/auth/entity/00270524","sameAs":"http://ja.dbpedia.org/resource/光厳天皇"},{"@id":"http://id.ndl.go.jp/auth/entity/00275687","sameAs":"http://ja.dbpedia.org/resource/冷泉為相"},{"@id":"http://id.ndl.go.jp/auth/entity/00866973","sameAs":"http://ja.dbpedia.org/resource/冷泉為秀"},{"@id":"http://id.ndl.go.jp/auth/entity/00270692","sameAs":"http://ja.dbpedia.org/resource/京極為兼"},{"@id":"http://id.ndl.go.jp/auth/entity/00421968","sameAs":"http://ja.dbpedia.org/resource/二条為世"},{"@id":"http://id.ndl.go.jp/auth/entity/00662416","sameAs":"http://ja.dbpedia.org/resource/二条為定"},{"@id":"http://id.ndl.go.jp/auth/entity/00095198","sameAs":"http://ja.dbpedia.org/resource/簗瀬一雄"}]}