{"@context":{"sameAs":{"@id":"http://www.w3.org/2002/07/owl#sameAs","@type":"@id"},"knows":"http://xmlns.com/foaf/0.1/knows"},"@id":"http://id.ndl.go.jp/auth/entity/00313341","sameAs":"http://ja.dbpedia.org/resource/林銑十郎","knows":[{"@id":"http://id.ndl.go.jp/auth/entity/00064849","sameAs":"http://ja.dbpedia.org/resource/西園寺公望"},{"@id":"http://id.ndl.go.jp/auth/entity/00064147","sameAs":"http://ja.dbpedia.org/resource/尾崎行雄"},{"@id":"http://id.ndl.go.jp/auth/entity/00257328","sameAs":"http://ja.dbpedia.org/resource/末次信正"},{"@id":"http://id.ndl.go.jp/auth/entity/00002983","sameAs":"http://ja.dbpedia.org/resource/荒木貞夫"},{"@id":"http://id.ndl.go.jp/auth/entity/00131254","sameAs":"http://ja.dbpedia.org/resource/巌本善治"},{"@id":"http://id.ndl.go.jp/auth/entity/00151639","sameAs":"http://ja.dbpedia.org/resource/中山博道"},{"@id":"http://id.ndl.go.jp/auth/entity/00314710","sameAs":"http://ja.dbpedia.org/resource/小川平吉"},{"@id":"http://id.ndl.go.jp/auth/entity/00339613","sameAs":"http://ja.dbpedia.org/resource/浅原健三"},{"@id":"http://id.ndl.go.jp/auth/entity/00095569","sameAs":"http://ja.dbpedia.org/resource/安井英二"},{"@id":"http://id.ndl.go.jp/auth/entity/00085162","sameAs":"http://ja.dbpedia.org/resource/富田勇太郎"},{"@id":"http://id.ndl.go.jp/auth/entity/00068345","sameAs":"http://ja.dbpedia.org/resource/佐藤尚武"},{"@id":"http://id.ndl.go.jp/auth/entity/00008710","sameAs":"http://ja.dbpedia.org/resource/畑俊六"},{"@id":"http://id.ndl.go.jp/auth/entity/001103933","sameAs":"http://ja.dbpedia.org/resource/閑院宮載仁親王"},{"@id":"http://id.ndl.go.jp/auth/entity/00035564","sameAs":"http://ja.dbpedia.org/resource/近衛文麿"},{"@id":"http://id.ndl.go.jp/auth/entity/00625750","sameAs":"http://ja.dbpedia.org/resource/渡辺錠太郎"},{"@id":"http://id.ndl.go.jp/auth/entity/00054902","sameAs":"http://ja.dbpedia.org/resource/西原亀三"},{"@id":"http://id.ndl.go.jp/auth/entity/00030361","sameAs":"http://ja.dbpedia.org/resource/木戸幸一"},{"@id":"http://id.ndl.go.jp/auth/entity/00045559","sameAs":"http://ja.dbpedia.org/resource/宮崎正義"},{"@id":"http://id.ndl.go.jp/auth/entity/00363945","sameAs":"http://ja.dbpedia.org/resource/愛新覚羅溥儀"},{"@id":"http://id.ndl.go.jp/auth/entity/00073440","sameAs":"http://ja.dbpedia.org/resource/十河信二"},{"@id":"http://id.ndl.go.jp/auth/entity/00625377","sameAs":"http://ja.dbpedia.org/resource/中村四郎_(内務官僚)"},{"@id":"http://id.ndl.go.jp/auth/entity/00083479","sameAs":"http://ja.dbpedia.org/resource/昭和天皇"},{"@id":"http://id.ndl.go.jp/auth/entity/00416012","sameAs":"http://ja.dbpedia.org/resource/前田利為"},{"@id":"http://id.ndl.go.jp/auth/entity/00329455","sameAs":"http://ja.dbpedia.org/resource/永田鉄山"},{"@id":"http://id.ndl.go.jp/auth/entity/00485944","sameAs":"http://ja.dbpedia.org/resource/金谷範三"},{"@id":"http://id.ndl.go.jp/auth/entity/00106482","sameAs":"http://ja.dbpedia.org/resource/佐藤朝泰"},{"@id":"http://id.ndl.go.jp/auth/entity/00011074","sameAs":"http://ja.dbpedia.org/resource/平生釟三郎"},{"@id":"http://id.ndl.go.jp/auth/entity/00341897","sameAs":"http://ja.dbpedia.org/resource/広田弘毅"},{"@id":"http://id.ndl.go.jp/auth/entity/00020740","sameAs":"http://ja.dbpedia.org/resource/石原莞爾"},{"@id":"http://id.ndl.go.jp/auth/entity/00003275","sameAs":"http://ja.dbpedia.org/resource/有田八郎"},{"@id":"http://id.ndl.go.jp/auth/entity/00326206","sameAs":"http://ja.dbpedia.org/resource/神田正種"},{"@id":"http://id.ndl.go.jp/auth/entity/00040402","sameAs":"http://ja.dbpedia.org/resource/真崎甚三郎"},{"@id":"http://id.ndl.go.jp/auth/entity/00318804","sameAs":"http://ja.dbpedia.org/resource/山本五十六"},{"@id":"http://id.ndl.go.jp/auth/entity/00622634","sameAs":"http://ja.dbpedia.org/resource/牛島満"},{"@id":"http://id.ndl.go.jp/auth/entity/00003214","sameAs":"http://ja.dbpedia.org/resource/有馬頼寧"},{"@id":"http://id.ndl.go.jp/auth/entity/00109679","sameAs":"http://ja.dbpedia.org/resource/米内光政"}]}