{"@context":{"sameAs":{"@id":"http://www.w3.org/2002/07/owl#sameAs","@type":"@id"},"knows":"http://xmlns.com/foaf/0.1/knows"},"@id":"http://id.ndl.go.jp/auth/entity/00333545","sameAs":"http://ja.dbpedia.org/resource/井田誠一","knows":[{"@id":"http://id.ndl.go.jp/auth/entity/01042152","sameAs":"http://ja.dbpedia.org/resource/利根一郎"},{"@id":"http://id.ndl.go.jp/auth/entity/00006477","sameAs":"http://ja.dbpedia.org/resource/灰田勝彦"},{"@id":"http://id.ndl.go.jp/auth/entity/00136728","sameAs":"http://ja.dbpedia.org/resource/雪村いづみ"},{"@id":"http://id.ndl.go.jp/auth/entity/001152111","sameAs":"http://ja.dbpedia.org/resource/ヴィクター・ヤング"},{"@id":"http://id.ndl.go.jp/auth/entity/00669669","sameAs":"http://ja.dbpedia.org/resource/佐野鋤"},{"@id":"http://id.ndl.go.jp/auth/entity/00009101","sameAs":"http://ja.dbpedia.org/resource/服部良一"},{"@id":"http://id.ndl.go.jp/auth/entity/01048937","sameAs":"http://ja.dbpedia.org/resource/松井八郎"},{"@id":"http://id.ndl.go.jp/auth/entity/01149509","sameAs":"http://ja.dbpedia.org/resource/吉田正"},{"@id":"http://id.ndl.go.jp/auth/entity/00625604","sameAs":"http://ja.dbpedia.org/resource/鶴田浩二"}]}