{"@context":{"sameAs":{"@id":"http://www.w3.org/2002/07/owl#sameAs","@type":"@id"},"knows":"http://xmlns.com/foaf/0.1/knows"},"@id":"http://id.ndl.go.jp/auth/entity/00427684","sameAs":"http://ja.dbpedia.org/resource/田渕久美子","knows":[{"@id":"http://id.ndl.go.jp/auth/entity/01215720","sameAs":"http://ja.dbpedia.org/resource/常高院"},{"@id":"http://id.ndl.go.jp/auth/entity/01209973","sameAs":"http://ja.dbpedia.org/resource/崇源院"},{"@id":"http://id.ndl.go.jp/auth/entity/00092225","sameAs":"http://ja.dbpedia.org/resource/山田太一_(脚本家)"},{"@id":"http://id.ndl.go.jp/auth/entity/00072205","sameAs":"http://ja.dbpedia.org/resource/新藤兼人"},{"@id":"http://id.ndl.go.jp/auth/entity/01037768","sameAs":"http://ja.dbpedia.org/resource/安住紳一郎"},{"@id":"http://id.ndl.go.jp/auth/entity/00172433","sameAs":"http://ja.dbpedia.org/resource/一色伸幸"},{"@id":"http://id.ndl.go.jp/auth/entity/00194635","sameAs":"http://ja.dbpedia.org/resource/太田宏美"}]}