{"@context":{"sameAs":{"@id":"http://www.w3.org/2002/07/owl#sameAs","@type":"@id"},"knows":"http://xmlns.com/foaf/0.1/knows"},"@id":"http://id.ndl.go.jp/auth/entity/00420134","sameAs":"http://ja.dbpedia.org/resource/小林泰三","knows":[{"@id":"http://id.ndl.go.jp/auth/entity/01006726","sameAs":"http://ja.dbpedia.org/resource/田中麗奈"},{"@id":"http://id.ndl.go.jp/auth/entity/00873105","sameAs":"http://ja.dbpedia.org/resource/大杉漣"},{"@id":"http://id.ndl.go.jp/auth/entity/00188902","sameAs":"http://ja.dbpedia.org/resource/MEIMU"},{"@id":"http://id.ndl.go.jp/auth/entity/00654321","sameAs":"http://ja.dbpedia.org/resource/鶴田謙二"},{"@id":"http://id.ndl.go.jp/auth/entity/00207931","sameAs":"http://ja.dbpedia.org/resource/麻耶雄嵩"},{"@id":"http://id.ndl.go.jp/auth/entity/00402223","sameAs":"http://ja.dbpedia.org/resource/林譲治_(作家)"},{"@id":"http://id.ndl.go.jp/auth/entity/00322578","sameAs":"http://ja.dbpedia.org/resource/田中啓文"},{"@id":"http://id.ndl.go.jp/auth/entity/00337092","sameAs":"http://ja.dbpedia.org/resource/牧野修"},{"@id":"http://id.ndl.go.jp/auth/entity/00332821","sameAs":"http://ja.dbpedia.org/resource/田中哲弥"}]}