{"@context":{"sameAs":{"@id":"http://www.w3.org/2002/07/owl#sameAs","@type":"@id"},"knows":"http://xmlns.com/foaf/0.1/knows"},"@id":"http://id.ndl.go.jp/auth/entity/00430078","sameAs":"http://ja.dbpedia.org/resource/飯島直子","knows":[{"@id":"http://id.ndl.go.jp/auth/entity/00825660","sameAs":"http://ja.dbpedia.org/resource/優香"},{"@id":"http://id.ndl.go.jp/auth/entity/00153569","sameAs":"http://ja.dbpedia.org/resource/中山美穂"},{"@id":"http://id.ndl.go.jp/auth/entity/00921877","sameAs":"http://ja.dbpedia.org/resource/井川遥"},{"@id":"http://id.ndl.go.jp/auth/entity/00170652","sameAs":"http://ja.dbpedia.org/resource/村西とおる"},{"@id":"http://id.ndl.go.jp/auth/entity/00737729","sameAs":"http://ja.dbpedia.org/resource/亜蘭知子"},{"@id":"http://id.ndl.go.jp/auth/entity/00815992","sameAs":"http://ja.dbpedia.org/resource/向井亜紀"},{"@id":"http://id.ndl.go.jp/auth/entity/00811427","sameAs":"http://ja.dbpedia.org/resource/深田恭子"},{"@id":"http://id.ndl.go.jp/auth/entity/00221147","sameAs":"http://ja.dbpedia.org/resource/宮本亜門"},{"@id":"http://id.ndl.go.jp/auth/entity/00212390","sameAs":"http://ja.dbpedia.org/resource/三谷幸喜"},{"@id":"http://id.ndl.go.jp/auth/entity/00185558","sameAs":"http://ja.dbpedia.org/resource/石橋貴明"},{"@id":"http://id.ndl.go.jp/auth/entity/00218973","sameAs":"http://ja.dbpedia.org/resource/久保田利伸"},{"@id":"http://id.ndl.go.jp/auth/entity/00417625","sameAs":"http://ja.dbpedia.org/resource/杉原千畝"},{"@id":"http://id.ndl.go.jp/auth/entity/00819534","sameAs":"http://ja.dbpedia.org/resource/小泉今日子"},{"@id":"http://id.ndl.go.jp/auth/entity/00181734","sameAs":"http://ja.dbpedia.org/resource/乃南アサ"},{"@id":"http://id.ndl.go.jp/auth/entity/00841305","sameAs":"http://ja.dbpedia.org/resource/松本明子"},{"@id":"http://id.ndl.go.jp/auth/entity/00333648","sameAs":"http://ja.dbpedia.org/resource/伊集院光"},{"@id":"http://id.ndl.go.jp/auth/entity/00166399","sameAs":"http://ja.dbpedia.org/resource/秋元康"},{"@id":"http://id.ndl.go.jp/auth/entity/00926057","sameAs":"http://ja.dbpedia.org/resource/上戸彩"},{"@id":"http://id.ndl.go.jp/auth/entity/00214443","sameAs":"http://ja.dbpedia.org/resource/田中美佐子"},{"@id":"http://id.ndl.go.jp/auth/entity/00341260","sameAs":"http://ja.dbpedia.org/resource/中山秀征"}]}