{"@context":{"sameAs":{"@id":"http://www.w3.org/2002/07/owl#sameAs","@type":"@id"},"knows":"http://xmlns.com/foaf/0.1/knows"},"@id":"http://id.ndl.go.jp/auth/entity/00466878","sameAs":"http://ja.dbpedia.org/resource/セルジュ・ゲンスブール","knows":[{"@id":"http://id.ndl.go.jp/auth/entity/00453304","sameAs":"http://ja.dbpedia.org/resource/ジャック・プレヴェール"},{"@id":"http://id.ndl.go.jp/auth/entity/00432536","sameAs":"http://ja.dbpedia.org/resource/シャルル・ボードレール"},{"@id":"http://id.ndl.go.jp/auth/entity/00435950","sameAs":"http://ja.dbpedia.org/resource/フレデリック・ショパン"},{"@id":"http://id.ndl.go.jp/auth/entity/00455343","sameAs":"http://ja.dbpedia.org/resource/ジャン＝ポール・サルトル"},{"@id":"http://id.ndl.go.jp/auth/entity/00620324","sameAs":"http://ja.dbpedia.org/resource/ブリジット・バルドー"},{"@id":"http://id.ndl.go.jp/auth/entity/00448881","sameAs":"http://ja.dbpedia.org/resource/ボブ・マーリー"},{"@id":"http://id.ndl.go.jp/auth/entity/00459722","sameAs":"http://ja.dbpedia.org/resource/ボリス・ヴィアン"},{"@id":"http://id.ndl.go.jp/auth/entity/00988826","sameAs":"http://ja.dbpedia.org/resource/リタ・マーリー"},{"@id":"http://id.ndl.go.jp/auth/entity/00451342","sameAs":"http://ja.dbpedia.org/resource/フリードリヒ・ニーチェ"},{"@id":"http://id.ndl.go.jp/auth/entity/01029690","sameAs":"http://ja.dbpedia.org/resource/ジョアン・スファール"},{"@id":"http://id.ndl.go.jp/auth/entity/00649769","sameAs":"http://ja.dbpedia.org/resource/ホイットニー・ヒューストン"},{"@id":"http://id.ndl.go.jp/auth/entity/00447148","sameAs":"http://ja.dbpedia.org/resource/ミシェル・ルブラン"},{"@id":"http://id.ndl.go.jp/auth/entity/00522683","sameAs":"http://ja.dbpedia.org/resource/ビリー・ホリデイ"},{"@id":"http://id.ndl.go.jp/auth/entity/00618105","sameAs":"http://ja.dbpedia.org/resource/戸田誠司"}]}