{"@context":{"sameAs":{"@id":"http://www.w3.org/2002/07/owl#sameAs","@type":"@id"},"knows":"http://xmlns.com/foaf/0.1/knows"},"@id":"http://id.ndl.go.jp/auth/entity/00521812","sameAs":"http://ja.dbpedia.org/resource/ロン・フラー","knows":[{"@id":"http://id.ndl.go.jp/auth/entity/00442590","sameAs":"http://ja.dbpedia.org/resource/ハーバート・ハート"},{"@id":"http://id.ndl.go.jp/auth/entity/00019127","sameAs":"http://ja.dbpedia.org/resource/稲垣良典"},{"@id":"http://id.ndl.go.jp/auth/entity/00015626","sameAs":"http://ja.dbpedia.org/resource/藤倉皓一郎"},{"@id":"http://id.ndl.go.jp/auth/entity/00437248","sameAs":"http://ja.dbpedia.org/resource/チャールズ・ダーウィン"},{"@id":"http://id.ndl.go.jp/auth/entity/00457285","sameAs":"http://ja.dbpedia.org/resource/ハーバート・スペンサー"},{"@id":"http://id.ndl.go.jp/auth/entity/00458645","sameAs":"http://ja.dbpedia.org/resource/トマス・アクィナス"},{"@id":"http://id.ndl.go.jp/auth/entity/00525381","sameAs":"http://ja.dbpedia.org/resource/グスタフ・ラートブルフ"},{"@id":"http://id.ndl.go.jp/auth/entity/00453210","sameAs":"http://ja.dbpedia.org/resource/ロスコー・パウンド"},{"@id":"http://id.ndl.go.jp/auth/entity/00437095","sameAs":"http://ja.dbpedia.org/resource/アレクサンダー・パッセリン・ダントレーヴ"}]}