{"@context":{"sameAs":{"@id":"http://www.w3.org/2002/07/owl#sameAs","@type":"@id"},"knows":"http://xmlns.com/foaf/0.1/knows"},"@id":"http://id.ndl.go.jp/auth/entity/00552209","sameAs":"http://ja.dbpedia.org/resource/デヴィッド・O・セルズニック","knows":[{"@id":"http://id.ndl.go.jp/auth/entity/00620571","sameAs":"http://ja.dbpedia.org/resource/アラン・ドロン"},{"@id":"http://id.ndl.go.jp/auth/entity/00522486","sameAs":"http://ja.dbpedia.org/resource/ベン・ヘクト"},{"@id":"http://id.ndl.go.jp/auth/entity/001118286","sameAs":"http://ja.dbpedia.org/resource/アルフレッド・ニューマン"},{"@id":"http://id.ndl.go.jp/auth/entity/00433022","sameAs":"http://ja.dbpedia.org/resource/イングリッド・バーグマン"},{"@id":"http://id.ndl.go.jp/auth/entity/00443431","sameAs":"http://ja.dbpedia.org/resource/アルフレッド・ヒッチコック"},{"@id":"http://id.ndl.go.jp/auth/entity/00476044","sameAs":"http://ja.dbpedia.org/resource/シャーリー・テンプル"},{"@id":"http://id.ndl.go.jp/auth/entity/00451751","sameAs":"http://ja.dbpedia.org/resource/ローレンス・オリヴィエ"},{"@id":"http://id.ndl.go.jp/auth/entity/00620993","sameAs":"http://ja.dbpedia.org/resource/ヴィヴィアン・リー"},{"@id":"http://id.ndl.go.jp/auth/entity/00620707","sameAs":"http://ja.dbpedia.org/resource/グレタ・ガルボ"}]}