{"@context":{"sameAs":{"@id":"http://www.w3.org/2002/07/owl#sameAs","@type":"@id"},"knows":"http://xmlns.com/foaf/0.1/knows"},"@id":"http://id.ndl.go.jp/auth/entity/00622752","sameAs":"http://ja.dbpedia.org/resource/熊谷直実","knows":[{"@id":"http://id.ndl.go.jp/auth/entity/00269424","sameAs":"http://ja.dbpedia.org/resource/法然"},{"@id":"http://id.ndl.go.jp/auth/entity/00085144","sameAs":"http://ja.dbpedia.org/resource/富田常雄"},{"@id":"http://id.ndl.go.jp/auth/entity/00270626","sameAs":"http://ja.dbpedia.org/resource/熊谷直好"},{"@id":"http://id.ndl.go.jp/auth/entity/00051680","sameAs":"http://ja.dbpedia.org/resource/中村吉右衛門_(初代)"},{"@id":"http://id.ndl.go.jp/auth/entity/00271103","sameAs":"http://ja.dbpedia.org/resource/中村歌右衛門_(3代目)"},{"@id":"http://id.ndl.go.jp/auth/entity/00281599","sameAs":"http://ja.dbpedia.org/resource/中村吉右衛門_(2代目)"},{"@id":"http://id.ndl.go.jp/auth/entity/00622848","sameAs":"http://ja.dbpedia.org/resource/源頼朝"},{"@id":"http://id.ndl.go.jp/auth/entity/00484319","sameAs":"http://ja.dbpedia.org/resource/菊池容斎"},{"@id":"http://id.ndl.go.jp/auth/entity/00622845","sameAs":"http://ja.dbpedia.org/resource/源範頼"},{"@id":"http://id.ndl.go.jp/auth/entity/00021001","sameAs":"http://ja.dbpedia.org/resource/石井進_(歴史学者)"},{"@id":"http://id.ndl.go.jp/auth/entity/00033806","sameAs":"http://ja.dbpedia.org/resource/児玉幸多"},{"@id":"http://id.ndl.go.jp/auth/entity/00129218","sameAs":"http://ja.dbpedia.org/resource/阿満利麿"},{"@id":"http://id.ndl.go.jp/auth/entity/001098521","sameAs":"http://ja.dbpedia.org/resource/源義朝"},{"@id":"http://id.ndl.go.jp/auth/entity/00058656","sameAs":"http://ja.dbpedia.org/resource/大橋俊雄"},{"@id":"http://id.ndl.go.jp/auth/entity/00026910","sameAs":"http://ja.dbpedia.org/resource/笠原一男"},{"@id":"http://id.ndl.go.jp/auth/entity/00032314","sameAs":"http://ja.dbpedia.org/resource/北村西望"},{"@id":"http://id.ndl.go.jp/auth/entity/00269851","sameAs":"http://ja.dbpedia.org/resource/九条兼実"},{"@id":"http://id.ndl.go.jp/auth/entity/00626366","sameAs":"http://ja.dbpedia.org/resource/平敦盛"},{"@id":"http://id.ndl.go.jp/auth/entity/00043502","sameAs":"http://ja.dbpedia.org/resource/三波春夫"},{"@id":"http://id.ndl.go.jp/auth/entity/00626362","sameAs":"http://ja.dbpedia.org/resource/北条政子"},{"@id":"http://id.ndl.go.jp/auth/entity/00622842","sameAs":"http://ja.dbpedia.org/resource/源義経"},{"@id":"http://id.ndl.go.jp/auth/entity/00088587","sameAs":"http://ja.dbpedia.org/resource/梅原猛"},{"@id":"http://id.ndl.go.jp/auth/entity/00626365","sameAs":"http://ja.dbpedia.org/resource/平知盛"},{"@id":"http://id.ndl.go.jp/auth/entity/00220621","sameAs":"http://ja.dbpedia.org/resource/山折哲雄"},{"@id":"http://id.ndl.go.jp/auth/entity/00101347","sameAs":"http://ja.dbpedia.org/resource/伊藤唯真"},{"@id":"http://id.ndl.go.jp/auth/entity/00216683","sameAs":"http://ja.dbpedia.org/resource/浅田次郎"},{"@id":"http://id.ndl.go.jp/auth/entity/00014899","sameAs":"http://ja.dbpedia.org/resource/古田武彦"},{"@id":"http://id.ndl.go.jp/auth/entity/00086001","sameAs":"http://ja.dbpedia.org/resource/坪井俊映"},{"@id":"http://id.ndl.go.jp/auth/entity/00622338","sameAs":"http://ja.dbpedia.org/resource/梶原景時"},{"@id":"http://id.ndl.go.jp/auth/entity/01111420","sameAs":"http://ja.dbpedia.org/resource/鳥羽天皇"},{"@id":"http://id.ndl.go.jp/auth/entity/00623712","sameAs":"http://ja.dbpedia.org/resource/市川團十郎_(12代目)"}]}