{"@context":{"sameAs":{"@id":"http://www.w3.org/2002/07/owl#sameAs","@type":"@id"},"knows":"http://xmlns.com/foaf/0.1/knows"},"@id":"http://id.ndl.go.jp/auth/entity/00620722","sameAs":"http://ja.dbpedia.org/resource/リチャード・ギア","knows":[{"@id":"http://id.ndl.go.jp/auth/entity/00194644","sameAs":"http://ja.dbpedia.org/resource/大竹まこと"},{"@id":"http://id.ndl.go.jp/auth/entity/00323057","sameAs":"http://ja.dbpedia.org/resource/臼井儀人"},{"@id":"http://id.ndl.go.jp/auth/entity/00445351","sameAs":"http://ja.dbpedia.org/resource/ジョン・A・キール"},{"@id":"http://id.ndl.go.jp/auth/entity/00826244","sameAs":"http://ja.dbpedia.org/resource/ジョージ・W・ブッシュ"},{"@id":"http://id.ndl.go.jp/auth/entity/00621731","sameAs":"http://ja.dbpedia.org/resource/渥美清"},{"@id":"http://id.ndl.go.jp/auth/entity/00038414","sameAs":"http://ja.dbpedia.org/resource/黒澤明"},{"@id":"http://id.ndl.go.jp/auth/entity/00365812","sameAs":"http://ja.dbpedia.org/resource/小泉純一郎"},{"@id":"http://id.ndl.go.jp/auth/entity/00084300","sameAs":"http://ja.dbpedia.org/resource/戸田奈津子"},{"@id":"http://id.ndl.go.jp/auth/entity/00451263","sameAs":"http://ja.dbpedia.org/resource/ダライ・ラマ14世"},{"@id":"http://id.ndl.go.jp/auth/entity/00620275","sameAs":"http://ja.dbpedia.org/resource/ヤーセル・アラファート"},{"@id":"http://id.ndl.go.jp/auth/entity/00559005","sameAs":"http://ja.dbpedia.org/resource/シンディ・クロフォード"},{"@id":"http://id.ndl.go.jp/auth/entity/00143269","sameAs":"http://ja.dbpedia.org/resource/みうらじゅん"},{"@id":"http://id.ndl.go.jp/auth/entity/00824897","sameAs":"http://ja.dbpedia.org/resource/山寺宏一"},{"@id":"http://id.ndl.go.jp/auth/entity/00515804","sameAs":"http://ja.dbpedia.org/resource/ハーブ・リッツ"},{"@id":"http://id.ndl.go.jp/auth/entity/00432205","sameAs":"http://ja.dbpedia.org/resource/バルテュス"},{"@id":"http://id.ndl.go.jp/auth/entity/00707780","sameAs":"http://ja.dbpedia.org/resource/トッド・ヘインズ"},{"@id":"http://id.ndl.go.jp/auth/entity/00621384","sameAs":"http://ja.dbpedia.org/resource/ジュリア・ロバーツ"},{"@id":"http://id.ndl.go.jp/auth/entity/00621624","sameAs":"http://ja.dbpedia.org/resource/トム・ウェイツ"},{"@id":"http://id.ndl.go.jp/auth/entity/00366923","sameAs":"http://ja.dbpedia.org/resource/松井秀喜"},{"@id":"http://id.ndl.go.jp/auth/entity/00465947","sameAs":"http://ja.dbpedia.org/resource/アメリア・イアハート"},{"@id":"http://id.ndl.go.jp/auth/entity/00441621","sameAs":"http://ja.dbpedia.org/resource/グレアム・グリーン"},{"@id":"http://id.ndl.go.jp/auth/entity/001217602","sameAs":"http://ja.dbpedia.org/resource/松本秀夫"},{"@id":"http://id.ndl.go.jp/auth/entity/00192209","sameAs":"http://ja.dbpedia.org/resource/田中眞紀子"}]}