{"@context":{"sameAs":{"@id":"http://www.w3.org/2002/07/owl#sameAs","@type":"@id"},"knows":"http://xmlns.com/foaf/0.1/knows"},"@id":"http://id.ndl.go.jp/auth/entity/00625490","sameAs":"http://ja.dbpedia.org/resource/朝吹英二","knows":[{"@id":"http://id.ndl.go.jp/auth/entity/00064147","sameAs":"http://ja.dbpedia.org/resource/尾崎行雄"},{"@id":"http://id.ndl.go.jp/auth/entity/00003355","sameAs":"http://ja.dbpedia.org/resource/朝吹登水子"},{"@id":"http://id.ndl.go.jp/auth/entity/00085849","sameAs":"http://ja.dbpedia.org/resource/豊川良平"},{"@id":"http://id.ndl.go.jp/auth/entity/00073078","sameAs":"http://ja.dbpedia.org/resource/白崎秀雄"},{"@id":"http://id.ndl.go.jp/auth/entity/00099110","sameAs":"http://ja.dbpedia.org/resource/朝吹亮二"},{"@id":"http://id.ndl.go.jp/auth/entity/00054196","sameAs":"http://ja.dbpedia.org/resource/名取洋之助"},{"@id":"http://id.ndl.go.jp/auth/entity/00348381","sameAs":"http://ja.dbpedia.org/resource/益田孝"},{"@id":"http://id.ndl.go.jp/auth/entity/00112932","sameAs":"http://ja.dbpedia.org/resource/野依良治"},{"@id":"http://id.ndl.go.jp/auth/entity/00344153","sameAs":"http://ja.dbpedia.org/resource/白石照山"},{"@id":"http://id.ndl.go.jp/auth/entity/01214235","sameAs":"http://ja.dbpedia.org/resource/朝吹真理子"},{"@id":"http://id.ndl.go.jp/auth/entity/00091330","sameAs":"http://ja.dbpedia.org/resource/渡辺世祐"},{"@id":"http://id.ndl.go.jp/auth/entity/00003354","sameAs":"http://ja.dbpedia.org/resource/朝吹三吉"},{"@id":"http://id.ndl.go.jp/auth/entity/00501630","sameAs":"http://ja.dbpedia.org/resource/中上川彦次郎"},{"@id":"http://id.ndl.go.jp/auth/entity/00624714","sameAs":"http://ja.dbpedia.org/resource/石田三成"},{"@id":"http://id.ndl.go.jp/auth/entity/00049414","sameAs":"http://ja.dbpedia.org/resource/武藤山治"},{"@id":"http://id.ndl.go.jp/auth/entity/00056789","sameAs":"http://ja.dbpedia.org/resource/野依秀市"},{"@id":"http://id.ndl.go.jp/auth/entity/00710633","sameAs":"http://ja.dbpedia.org/resource/團琢磨"},{"@id":"http://id.ndl.go.jp/auth/entity/00625491","sameAs":"http://ja.dbpedia.org/resource/朝吹常吉"},{"@id":"http://id.ndl.go.jp/auth/entity/00269787","sameAs":"http://ja.dbpedia.org/resource/福澤諭吉"},{"@id":"http://id.ndl.go.jp/auth/entity/00060807","sameAs":"http://ja.dbpedia.org/resource/大隈重信"},{"@id":"http://id.ndl.go.jp/auth/entity/00626563","sameAs":"http://ja.dbpedia.org/resource/名取和作"},{"@id":"http://id.ndl.go.jp/auth/entity/001109991","sameAs":"http://ja.dbpedia.org/resource/速水堅曹"}]}