{"@context":{"sameAs":{"@id":"http://www.w3.org/2002/07/owl#sameAs","@type":"@id"},"knows":"http://xmlns.com/foaf/0.1/knows"},"@id":"http://id.ndl.go.jp/auth/entity/00648900","sameAs":"http://ja.dbpedia.org/resource/アントン・ルビンシテイン","knows":[{"@id":"http://id.ndl.go.jp/auth/entity/01186515","sameAs":"http://ja.dbpedia.org/resource/イグナーツ・ブリュル"},{"@id":"http://id.ndl.go.jp/auth/entity/00526435","sameAs":"http://ja.dbpedia.org/resource/ウラディーミル・スターソフ"},{"@id":"http://id.ndl.go.jp/auth/entity/00514611","sameAs":"http://ja.dbpedia.org/resource/ヨゼフ・レヴィーン"},{"@id":"http://id.ndl.go.jp/auth/entity/00454245","sameAs":"http://ja.dbpedia.org/resource/ニコライ・リムスキー＝コルサコフ"},{"@id":"http://id.ndl.go.jp/auth/entity/00455829","sameAs":"http://ja.dbpedia.org/resource/クララ・シューマン"},{"@id":"http://id.ndl.go.jp/auth/entity/00798527","sameAs":"http://ja.dbpedia.org/resource/エドワード・エルガー"},{"@id":"http://id.ndl.go.jp/auth/entity/00473354","sameAs":"http://ja.dbpedia.org/resource/セルゲイ・プロコフィエフ"},{"@id":"http://id.ndl.go.jp/auth/entity/00435632","sameAs":"http://ja.dbpedia.org/resource/ピョートル・チャイコフスキー"},{"@id":"http://id.ndl.go.jp/auth/entity/01163811","sameAs":"http://ja.dbpedia.org/resource/アドルフ・フォン・ヘンゼルト"},{"@id":"http://id.ndl.go.jp/auth/entity/00471518","sameAs":"http://ja.dbpedia.org/resource/フェリックス・メンデルスゾーン"},{"@id":"http://id.ndl.go.jp/auth/entity/00432740","sameAs":"http://ja.dbpedia.org/resource/ルートヴィヒ・ヴァン・ベートーヴェン"},{"@id":"http://id.ndl.go.jp/auth/entity/01140637","sameAs":"http://ja.dbpedia.org/resource/ジャコモ・マイアベーア"},{"@id":"http://id.ndl.go.jp/auth/entity/00454911","sameAs":"http://ja.dbpedia.org/resource/アルトゥール・ルービンシュタイン"},{"@id":"http://id.ndl.go.jp/auth/entity/00435950","sameAs":"http://ja.dbpedia.org/resource/フレデリック・ショパン"},{"@id":"http://id.ndl.go.jp/auth/entity/01052624","sameAs":"http://ja.dbpedia.org/resource/シャルル＝ヴァランタン・アルカン"},{"@id":"http://id.ndl.go.jp/auth/entity/00523887","sameAs":"http://ja.dbpedia.org/resource/フランツ・リスト"},{"@id":"http://id.ndl.go.jp/auth/entity/00648900","sameAs":"http://ja.dbpedia.org/resource/アントン・ルビンシテイン"},{"@id":"http://id.ndl.go.jp/auth/entity/00524218","sameAs":"http://ja.dbpedia.org/resource/アドルフ・ベルンハルト・マルクス"},{"@id":"http://id.ndl.go.jp/auth/entity/00454006","sameAs":"http://ja.dbpedia.org/resource/イリヤ・レーピン"},{"@id":"http://id.ndl.go.jp/auth/entity/00964761","sameAs":"http://ja.dbpedia.org/resource/アレクサンドル・グラズノフ"},{"@id":"http://id.ndl.go.jp/auth/entity/00901966","sameAs":"http://ja.dbpedia.org/resource/ツェーザリ・キュイ"},{"@id":"http://id.ndl.go.jp/auth/entity/00902598","sameAs":"http://ja.dbpedia.org/resource/ウジェーヌ・イザイ"},{"@id":"http://id.ndl.go.jp/auth/entity/00621460","sameAs":"http://ja.dbpedia.org/resource/アレクサンドル・スクリャービン"},{"@id":"http://id.ndl.go.jp/auth/entity/00468450","sameAs":"http://ja.dbpedia.org/resource/ヨゼフ・ホフマン"}]}