{"@context":{"sameAs":{"@id":"http://www.w3.org/2002/07/owl#sameAs","@type":"@id"},"knows":"http://xmlns.com/foaf/0.1/knows"},"@id":"http://id.ndl.go.jp/auth/entity/00659919","sameAs":"http://ja.dbpedia.org/resource/中村卓史","knows":[{"@id":"http://id.ndl.go.jp/auth/entity/00424255","sameAs":"http://ja.dbpedia.org/resource/佐々木節"},{"@id":"http://id.ndl.go.jp/auth/entity/00009815","sameAs":"http://ja.dbpedia.org/resource/林忠四郎"},{"@id":"http://id.ndl.go.jp/auth/entity/00068002","sameAs":"http://ja.dbpedia.org/resource/佐藤文隆"},{"@id":"http://id.ndl.go.jp/auth/entity/00214948","sameAs":"http://ja.dbpedia.org/resource/前田恵一"}]}