{"@context":{"sameAs":{"@id":"http://www.w3.org/2002/07/owl#sameAs","@type":"@id"},"knows":"http://xmlns.com/foaf/0.1/knows"},"@id":"http://id.ndl.go.jp/auth/entity/00677684","sameAs":"http://ja.dbpedia.org/resource/ゲイリー・オールドマン","knows":[{"@id":"http://id.ndl.go.jp/auth/entity/001200890","sameAs":"http://ja.dbpedia.org/resource/大塚明夫"},{"@id":"http://id.ndl.go.jp/auth/entity/00650307","sameAs":"http://ja.dbpedia.org/resource/ジョニー・デップ"},{"@id":"http://id.ndl.go.jp/auth/entity/001131217","sameAs":"http://ja.dbpedia.org/resource/松山ケンイチ"},{"@id":"http://id.ndl.go.jp/auth/entity/00621241","sameAs":"http://ja.dbpedia.org/resource/リー・ハーヴェイ・オズワルド"},{"@id":"http://id.ndl.go.jp/auth/entity/00620565","sameAs":"http://ja.dbpedia.org/resource/ロバート・デ・ニーロ"},{"@id":"http://id.ndl.go.jp/auth/entity/00824897","sameAs":"http://ja.dbpedia.org/resource/山寺宏一"},{"@id":"http://id.ndl.go.jp/auth/entity/00447071","sameAs":"http://ja.dbpedia.org/resource/ジョン・ル・カレ"},{"@id":"http://id.ndl.go.jp/auth/entity/01126315","sameAs":"http://ja.dbpedia.org/resource/デンゼル・ワシントン"},{"@id":"http://id.ndl.go.jp/auth/entity/001135135","sameAs":"http://ja.dbpedia.org/resource/ベネディクト・カンバーバッチ"},{"@id":"http://id.ndl.go.jp/auth/entity/00883235","sameAs":"http://ja.dbpedia.org/resource/田中亮一"}]}