{"@context":{"sameAs":{"@id":"http://www.w3.org/2002/07/owl#sameAs","@type":"@id"},"knows":"http://xmlns.com/foaf/0.1/knows"},"@id":"http://id.ndl.go.jp/auth/entity/00687176","sameAs":"http://ja.dbpedia.org/resource/松本和那","knows":[{"@id":"http://id.ndl.go.jp/auth/entity/00895252","sameAs":"http://ja.dbpedia.org/resource/松本和巳"},{"@id":"http://id.ndl.go.jp/auth/entity/00909127","sameAs":"http://ja.dbpedia.org/resource/坂本孝"},{"@id":"http://id.ndl.go.jp/auth/entity/00684258","sameAs":"http://ja.dbpedia.org/resource/大村秀章"},{"@id":"http://id.ndl.go.jp/auth/entity/00398387","sameAs":"http://ja.dbpedia.org/resource/谷畑孝"},{"@id":"http://id.ndl.go.jp/auth/entity/001124957","sameAs":"http://ja.dbpedia.org/resource/新藤義孝"},{"@id":"http://id.ndl.go.jp/auth/entity/00695437","sameAs":"http://ja.dbpedia.org/resource/戸井田徹"},{"@id":"http://id.ndl.go.jp/auth/entity/00846660","sameAs":"http://ja.dbpedia.org/resource/桜田義孝"},{"@id":"http://id.ndl.go.jp/auth/entity/00931265","sameAs":"http://ja.dbpedia.org/resource/河野太郎"},{"@id":"http://id.ndl.go.jp/auth/entity/00836604","sameAs":"http://ja.dbpedia.org/resource/渡辺喜美"},{"@id":"http://id.ndl.go.jp/auth/entity/00649109","sameAs":"http://ja.dbpedia.org/resource/松本清"},{"@id":"http://id.ndl.go.jp/auth/entity/00011155","sameAs":"http://ja.dbpedia.org/resource/平沢勝栄"},{"@id":"http://id.ndl.go.jp/auth/entity/00422260","sameAs":"http://ja.dbpedia.org/resource/滝実"},{"@id":"http://id.ndl.go.jp/auth/entity/00813523","sameAs":"http://ja.dbpedia.org/resource/下地幹郎"},{"@id":"http://id.ndl.go.jp/auth/entity/001103787","sameAs":"http://ja.dbpedia.org/resource/菅義偉"},{"@id":"http://id.ndl.go.jp/auth/entity/00141285","sameAs":"http://ja.dbpedia.org/resource/下村博文"}]}