{"@context":{"sameAs":{"@id":"http://www.w3.org/2002/07/owl#sameAs","@type":"@id"},"knows":"http://xmlns.com/foaf/0.1/knows"},"@id":"http://id.ndl.go.jp/auth/entity/00761405","sameAs":"http://ja.dbpedia.org/resource/光仁天皇","knows":[{"@id":"http://id.ndl.go.jp/auth/entity/01182925","sameAs":"http://ja.dbpedia.org/resource/称光天皇"},{"@id":"http://id.ndl.go.jp/auth/entity/00622357","sameAs":"http://ja.dbpedia.org/resource/桓武天皇"},{"@id":"http://id.ndl.go.jp/auth/entity/00271946","sameAs":"http://ja.dbpedia.org/resource/聖武天皇"},{"@id":"http://id.ndl.go.jp/auth/entity/00625627","sameAs":"http://ja.dbpedia.org/resource/天智天皇"},{"@id":"http://id.ndl.go.jp/auth/entity/00708292","sameAs":"http://ja.dbpedia.org/resource/孝謙天皇"},{"@id":"http://id.ndl.go.jp/auth/entity/00623422","sameAs":"http://ja.dbpedia.org/resource/坂上田村麻呂"},{"@id":"http://id.ndl.go.jp/auth/entity/00623922","sameAs":"http://ja.dbpedia.org/resource/淳仁天皇"},{"@id":"http://id.ndl.go.jp/auth/entity/01145032","sameAs":"http://ja.dbpedia.org/resource/四条天皇"},{"@id":"http://id.ndl.go.jp/auth/entity/00270821","sameAs":"http://ja.dbpedia.org/resource/源通親"},{"@id":"http://id.ndl.go.jp/auth/entity/00622550","sameAs":"http://ja.dbpedia.org/resource/吉備真備"},{"@id":"http://id.ndl.go.jp/auth/entity/00626913","sameAs":"http://ja.dbpedia.org/resource/和気清麻呂"},{"@id":"http://id.ndl.go.jp/auth/entity/001193422","sameAs":"http://ja.dbpedia.org/resource/藤原種継"},{"@id":"http://id.ndl.go.jp/auth/entity/00625905","sameAs":"http://ja.dbpedia.org/resource/藤原仲麻呂"},{"@id":"http://id.ndl.go.jp/auth/entity/00625951","sameAs":"http://ja.dbpedia.org/resource/道鏡"},{"@id":"http://id.ndl.go.jp/auth/entity/00625630","sameAs":"http://ja.dbpedia.org/resource/天武天皇"},{"@id":"http://id.ndl.go.jp/auth/entity/00271869","sameAs":"http://ja.dbpedia.org/resource/菅原道真"},{"@id":"http://id.ndl.go.jp/auth/entity/01189931","sameAs":"http://ja.dbpedia.org/resource/井上内親王"},{"@id":"http://id.ndl.go.jp/auth/entity/01142892","sameAs":"http://ja.dbpedia.org/resource/善珠"},{"@id":"http://id.ndl.go.jp/auth/entity/00271451","sameAs":"http://ja.dbpedia.org/resource/大伴家持"},{"@id":"http://id.ndl.go.jp/auth/entity/00271384","sameAs":"http://ja.dbpedia.org/resource/淡海三船"}]}