{"@context":{"sameAs":{"@id":"http://www.w3.org/2002/07/owl#sameAs","@type":"@id"},"knows":"http://xmlns.com/foaf/0.1/knows"},"@id":"http://id.ndl.go.jp/auth/entity/00913142","sameAs":"http://ja.dbpedia.org/resource/五百籏頭薫","knows":[{"@id":"http://id.ndl.go.jp/auth/entity/00146762","sameAs":"http://ja.dbpedia.org/resource/五百籏頭真"},{"@id":"http://id.ndl.go.jp/auth/entity/00329957","sameAs":"http://ja.dbpedia.org/resource/五百籏頭眞治郎"},{"@id":"http://id.ndl.go.jp/auth/entity/00215193","sameAs":"http://ja.dbpedia.org/resource/坂本一登"},{"@id":"http://id.ndl.go.jp/auth/entity/00719600","sameAs":"http://ja.dbpedia.org/resource/岡本隆司"},{"@id":"http://id.ndl.go.jp/auth/entity/00060807","sameAs":"http://ja.dbpedia.org/resource/大隈重信"},{"@id":"http://id.ndl.go.jp/auth/entity/00902484","sameAs":"http://ja.dbpedia.org/resource/川島真"},{"@id":"http://id.ndl.go.jp/auth/entity/00844753","sameAs":"http://ja.dbpedia.org/resource/服部龍二"},{"@id":"http://id.ndl.go.jp/auth/entity/00044015","sameAs":"http://ja.dbpedia.org/resource/三谷太一郎"}]}