{"@context":{"sameAs":{"@id":"http://www.w3.org/2002/07/owl#sameAs","@type":"@id"},"knows":"http://xmlns.com/foaf/0.1/knows"},"@id":"http://id.ndl.go.jp/auth/entity/00924294","sameAs":"http://ja.dbpedia.org/resource/市川実日子","knows":[{"@id":"http://id.ndl.go.jp/auth/entity/00092225","sameAs":"http://ja.dbpedia.org/resource/山田太一_(脚本家)"},{"@id":"http://id.ndl.go.jp/auth/entity/00098624","sameAs":"http://ja.dbpedia.org/resource/実相寺昭雄"},{"@id":"http://id.ndl.go.jp/auth/entity/01014245","sameAs":"http://ja.dbpedia.org/resource/前田司郎"},{"@id":"http://id.ndl.go.jp/auth/entity/00518734","sameAs":"http://ja.dbpedia.org/resource/庵野秀明"},{"@id":"http://id.ndl.go.jp/auth/entity/00428463","sameAs":"http://ja.dbpedia.org/resource/魚喃キリコ"},{"@id":"http://id.ndl.go.jp/auth/entity/00987064","sameAs":"http://ja.dbpedia.org/resource/荻上直子"},{"@id":"http://id.ndl.go.jp/auth/entity/01009929","sameAs":"http://ja.dbpedia.org/resource/大谷健太郎"},{"@id":"http://id.ndl.go.jp/auth/entity/00174380","sameAs":"http://ja.dbpedia.org/resource/吉本ばなな"},{"@id":"http://id.ndl.go.jp/auth/entity/00462563","sameAs":"http://ja.dbpedia.org/resource/ポール・オースター"},{"@id":"http://id.ndl.go.jp/auth/entity/00545813","sameAs":"http://ja.dbpedia.org/resource/中島哲也"},{"@id":"http://id.ndl.go.jp/auth/entity/00417506","sameAs":"http://ja.dbpedia.org/resource/塚本晋也"},{"@id":"http://id.ndl.go.jp/auth/entity/01037024","sameAs":"http://ja.dbpedia.org/resource/三木聡"},{"@id":"http://id.ndl.go.jp/auth/entity/00120440","sameAs":"http://ja.dbpedia.org/resource/吉田秋生"},{"@id":"http://id.ndl.go.jp/auth/entity/00413208","sameAs":"http://ja.dbpedia.org/resource/ホンマタカシ"},{"@id":"http://id.ndl.go.jp/auth/entity/00804497","sameAs":"http://ja.dbpedia.org/resource/田辺誠一"},{"@id":"http://id.ndl.go.jp/auth/entity/00980648","sameAs":"http://ja.dbpedia.org/resource/豊島圭介"},{"@id":"http://id.ndl.go.jp/auth/entity/00862327","sameAs":"http://ja.dbpedia.org/resource/川内倫子"},{"@id":"http://id.ndl.go.jp/auth/entity/00929517","sameAs":"http://ja.dbpedia.org/resource/佐藤江梨子"},{"@id":"http://id.ndl.go.jp/auth/entity/00557670","sameAs":"http://ja.dbpedia.org/resource/HIROMIX"}]}