{"@context":{"sameAs":{"@id":"http://www.w3.org/2002/07/owl#sameAs","@type":"@id"},"knows":"http://xmlns.com/foaf/0.1/knows"},"@id":"http://id.ndl.go.jp/auth/entity/00986539","sameAs":"http://ja.dbpedia.org/resource/ウィスット・ポンニミット","knows":[{"@id":"http://id.ndl.go.jp/auth/entity/00119060","sameAs":"http://ja.dbpedia.org/resource/あだち充"},{"@id":"http://id.ndl.go.jp/auth/entity/00083890","sameAs":"http://ja.dbpedia.org/resource/手塚治虫"},{"@id":"http://id.ndl.go.jp/auth/entity/00171426","sameAs":"http://ja.dbpedia.org/resource/田中政志"},{"@id":"http://id.ndl.go.jp/auth/entity/00120160","sameAs":"http://ja.dbpedia.org/resource/高橋葉介"},{"@id":"http://id.ndl.go.jp/auth/entity/00213752","sameAs":"http://ja.dbpedia.org/resource/飴屋法水"}]}