{"@context":{"sameAs":{"@id":"http://www.w3.org/2002/07/owl#sameAs","@type":"@id"},"knows":"http://xmlns.com/foaf/0.1/knows"},"@id":"http://id.ndl.go.jp/auth/entity/01004475","sameAs":"http://ja.dbpedia.org/resource/五味一男","knows":[{"@id":"http://id.ndl.go.jp/auth/entity/00824570","sameAs":"http://ja.dbpedia.org/resource/東野幸治"},{"@id":"http://id.ndl.go.jp/auth/entity/00150904","sameAs":"http://ja.dbpedia.org/resource/家田荘子"},{"@id":"http://id.ndl.go.jp/auth/entity/01074948","sameAs":"http://ja.dbpedia.org/resource/竹山隆範"},{"@id":"http://id.ndl.go.jp/auth/entity/00973924","sameAs":"http://ja.dbpedia.org/resource/波田陽区"},{"@id":"http://id.ndl.go.jp/auth/entity/00202774","sameAs":"http://ja.dbpedia.org/resource/市川準"},{"@id":"http://id.ndl.go.jp/auth/entity/00254412","sameAs":"http://ja.dbpedia.org/resource/君塚良一"}]}